README.rst
setup.cfg
setup.py
flask_typed_mounter/__init__.py
flask_typed_mounter/typed_mounter.py
flask_typed_mounter.egg-info/PKG-INFO
flask_typed_mounter.egg-info/SOURCES.txt
flask_typed_mounter.egg-info/dependency_links.txt
flask_typed_mounter.egg-info/requires.txt
flask_typed_mounter.egg-info/top_level.txt