Metadata-Version: 1.2
Name: flask-typed-mounter
Version: 0.1
Summary: Decorator to mount a function to a Flask endpoint
Home-page: https://github.com/jacopofar/flask-typed-mounter
Author: Jacopo Farina
Author-email: jacopo1.farina@gmail.com
License: MIT
Keywords: flask type hinting api mounter
Platform: UNKNOWN
Classifier: Development Status :: 3 - Alpha
Classifier: License :: OSI Approved :: MIT License
Classifier: Programming Language :: Python :: 3.6
Requires-Python: >=3.6
